{"data":[{"a":"42990705 ","b":6148.28,"c":0.0,"d":6148.28,"e":"ZEVALLOS RODRIGUEZ RUTH KATHERINE ","f":1888.0,"g":0.0,"h":1888.0},{"a":"44322315 ","b":2239.33,"c":0.0,"d":2239.33,"e":"ZAPATA PACHERREZ SEGUNDO LUIS ","f":690.3,"g":0.0,"h":690.3},{"a":"77043512 ","b":1649.56,"c":0.0,"d":1649.56,"e":"ZAPATA PACHERRESMARYCIELO SOLAYSH ","f":507.4,"g":0.0,"h":507.4},{"a":"10449565032","b":2878.91,"c":0.0,"d":2878.91,"e":"ZAMORA OCAS GABY ROXANA ","f":885.0,"g":0.0,"h":885.0},{"a":"10218545641","b":3678.77,"c":153.06,"d":3525.71,"e":"YATACODE LA CRUZ SANDRA MARIA ","f":1132.8,"g":54.14,"h":1078.66},{"a":"10410458352","b":6897.69,"c":0.0,"d":6897.69,"e":"YANCEMAVILA IDA RITA","f":2124.0,"g":0.0,"h":2124.0},{"a":"08160304 ","b":5756.92,"c":0.0,"d":5756.92,"e":"VISALOTH DEL AGUILA JUDITH","f":1770.0,"g":0.0,"h":1770.0},{"a":"10456750678","b":4396.11,"c":0.0,"d":4396.11,"e":"VILLEGAS PINTADOSILVIA","f":1345.2,"g":0.0,"h":1345.2},{"a":"40390869 ","b":8427.08,"c":0.0,"d":8427.08,"e":"VILLAVICENCIO QUISPE JOSE LUIS","f":2584.2,"g":0.0,"h":2584.2},{"a":"10466921063","b":1880.88,"c":0.0,"d":1880.88,"e":"VILLAGOMEZ APONTEGERALDINE XIOMARA","f":578.2,"g":0.0,"h":578.2},{"a":"10462244 ","b":4536.93,"c":0.0,"d":4536.93,"e":"VILLACORTARODRIGUEZ ANA ROCIO ","f":1353.5,"g":0.0,"h":1353.5},{"a":"41089167 ","b":5058.31,"c":0.0,"d":5058.31,"e":"VILLA ROZAS BETTY ","f":1557.6,"g":0.0,"h":1557.6},{"a":"42798802 ","b":17733.28,"c":0.0,"d":17733.28,"e":"VILCA PABLO INES GUISSELA ","f":5428.0,"g":0.0,"h":5428.0},{"a":"08641363 ","b":8872.07,"c":0.0,"d":8872.07,"e":"VERA RAMOS JUAN CARLOS","f":2714.0,"g":0.0,"h":2714.0},{"a":"08890019 ","b":1763.56,"c":0.0,"d":1763.56,"e":"VELASCO UMAYASIMARIA MAGDALENA","f":542.8,"g":0.0,"h":542.8},{"a":"07289341 ","b":899.84,"c":0.0,"d":899.84,"e":"VASQUEZ MONZONMAXIMA PERPETUA ","f":268.45,"g":0.0,"h":268.45},{"a":"20511433704","b":7.37,"c":46.13,"d":-38.76,"e":"VALLAS Y GIGANTOGRAFIAS DE PERU S.A.","f":3.23,"g":6.12,"h":-2.89},{"a":"07376950 ","b":4935.99,"c":1100.11,"d":3835.88,"e":"UEKADO GUIBO DE KINANA","f":1510.4,"g":338.8,"h":1171.6},{"a":"41802293 ","b":2298.88,"c":0.0,"d":2298.88,"e":"TTICA BOLAÑOS WILFREDO","f":708.0,"g":0.0,"h":708.0},{"a":"46741547 ","b":11321.16,"c":0.0,"d":11321.16,"e":"TTICAMAZA LUCY","f":3469.2,"g":0.0,"h":3469.2},{"a":"40279330 ","b":8777.42,"c":0.0,"d":8777.42,"e":"TTICABOLAÑOS MARTHA ","f":2690.4,"g":0.0,"h":2690.4},{"a":"44165428 ","b":4406.85,"c":0.0,"d":4406.85,"e":"TRUJILLANO MORE STEFANY ","f":1357.0,"g":0.0,"h":1357.0},{"a":"20601355222","b":13795.38,"c":1994.89,"d":11800.49,"e":"TRADE DLC S.A.C.","f":4248.0,"g":614.0,"h":3634.0},{"a":"16124441 ","b":1760.84,"c":0.0,"d":1760.84,"e":"TORRESDIAZ KATYA ELENA PAOLA","f":542.8,"g":0.0,"h":542.8},{"a":"10100554408","b":4628.9,"c":0.0,"d":4628.9,"e":"TORRECASTAÑEDA GIOVANNA ","f":1416.0,"g":0.0,"h":1416.0},{"a":"20544802969","b":34488.45,"c":0.0,"d":34488.45,"e":"TEXTIMODA NORTE S.A.C.","f":10620.0,"g":0.0,"h":10620.0},{"a":"42958170 ","b":5013.11,"c":0.0,"d":5013.11,"e":"TERRONES ESPINOZA ELVIS YIMI","f":1534.0,"g":0.0,"h":1534.0},{"a":"20600019903","b":8430.51,"c":0.0,"d":8430.51,"e":"TEILOR A.M S.A.C. ","f":2596.0,"g":0.0,"h":2596.0},{"a":"43494374 ","b":727.3,"c":0.0,"d":727.3,"e":"TAYPE HUARCAYA KEVIN ERASMO ","f":224.2,"g":0.0,"h":224.2},{"a":"10727330866","b":39.55,"c":0.0,"d":39.55,"e":"SOTOMAYOR SALGADO. STEPHANNY RUTH ","f":11.8,"g":0.0,"h":11.8},{"a":"48581287 ","b":54076.85,"c":0.0,"d":54076.85,"e":"SOTO CARDENASROSALINDA SIMONA ","f":16134.14,"g":0.0,"h":16134.14},{"a":"10074496950","b":1745.46,"c":0.0,"d":1745.46,"e":"SORIA CHANGA MIGUEL ESTEBAN ","f":536.9,"g":0.0,"h":536.9},{"a":"10502955 ","b":4622.53,"c":0.0,"d":4622.53,"e":"SOLIS RIMACHI ROSALIA ","f":1416.0,"g":0.0,"h":1416.0},{"a":"10074799804","b":3138.89,"c":0.0,"d":3138.89,"e":"SERRANOVASQUEZ ELIZABETH","f":967.6,"g":0.0,"h":967.6},{"a":"44205703 ","b":15410.91,"c":0.0,"d":15410.91,"e":"SANGAMA PEZO JORGE LUIS ","f":4672.8,"g":0.0,"h":4672.8},{"a":"40598177 ","b":8967.0,"c":0.0,"d":8967.0,"e":"SANCHEZ ZULUETA JOSE HERNAN ","f":2761.2,"g":0.0,"h":2761.2},{"a":"80027469 ","b":5379.73,"c":64.66,"d":5315.07,"e":"SANCHEZ NIÑO LUIS ENRIQUE ","f":1652.0,"g":19.9,"h":1632.1},{"a":"46609803 ","b":1668.73,"c":0.0,"d":1668.73,"e":"ROSALES CONCHA LUIS ALBERTO ","f":513.3,"g":0.0,"h":513.3},{"a":"10436358 ","b":2832.22,"c":0.0,"d":2832.22,"e":"ROMERO MENDOZAEXILDA YOLANDA","f":873.2,"g":0.0,"h":873.2},{"a":"44365873 ","b":1039.7,"c":0.0,"d":1039.7,"e":"ROMEROVALENCIA ROSA MARIA ","f":318.6,"g":0.0,"h":318.6},{"a":"40907945 ","b":3770.74,"c":0.0,"d":3770.74,"e":"ROMERORUIZ MARIA LUISA","f":1156.4,"g":0.0,"h":1156.4},{"a":"10103817442","b":4330.21,"c":0.0,"d":4330.21,"e":"ROMEROPORTAL EDITH ESTHER ","f":1333.4,"g":0.0,"h":1333.4},{"a":"10095617528","b":3857.42,"c":0.0,"d":3857.42,"e":"ROJAS TELLOELIZABETH NIEVES ","f":1180.0,"g":0.0,"h":1180.0},{"a":"47723408 ","b":4073.35,"c":0.0,"d":4073.35,"e":"ROJAS GARCILAZOHELEN LUISA","f":1215.2,"g":0.0,"h":1215.2},{"a":"10102144207","b":2682.43,"c":0.0,"d":2682.43,"e":"RODRIGUEZVELA ANA GABRIELA","f":826.0,"g":0.0,"h":826.0},{"a":"42204590 ","b":9605.69,"c":258.37,"d":9347.32,"e":"RIVERA ARCOSJESUS ALEJANDRO ","f":2955.9,"g":79.4,"h":2876.5},{"a":"09974815 ","b":1760.84,"c":0.0,"d":1760.84,"e":"RIOSCELIS VICTORIA CLARITA","f":542.8,"g":0.0,"h":542.8},{"a":"07099552 ","b":2723.69,"c":0.0,"d":2723.69,"e":"REYES ORTEGA VDA. DE ARCE ROSA TARCILA","f":837.8,"g":0.0,"h":837.8},{"a":"41922528 ","b":6442.14,"c":0.0,"d":6442.14,"e":"REAÑO COSQUILLOLOURDES ADELINDA ","f":1982.4,"g":0.0,"h":1982.4},{"a":"10072657476","b":5321.61,"c":0.0,"d":5321.61,"e":"RAMIREZ ZARATE LUZ ARACELLI ","f":1628.4,"g":0.0,"h":1628.4},{"a":"10400862619","b":3419.98,"c":0.0,"d":3419.98,"e":"RAMIREZ DEZAVILMA ELSA","f":1050.2,"g":0.0,"h":1050.2},{"a":"29473120 ","b":3106.03,"c":0.0,"d":3106.03,"e":"QUISPE QUISPE TEODOCIA","f":955.8,"g":0.0,"h":955.8},{"a":"44339762 ","b":31768.55,"c":0.0,"d":31768.55,"e":"QUISPE MENDOZA FLOR MARIA ","f":9735.0,"g":0.0,"h":9735.0},{"a":"47881445 ","b":746.44,"c":0.0,"d":746.44,"e":"QUISPE HUAYNA NELLY ","f":230.1,"g":0.0,"h":230.1},{"a":"10200536121","b":3428.43,"c":0.0,"d":3428.43,"e":"QUISPE CASTAÑEDA CRISTINA ELIZABETH ","f":1022.8,"g":0.0,"h":1022.8},{"a":"09804930 ","b":2911.91,"c":0.0,"d":2911.91,"e":"QUILCAOROSCO MARLON MICHAEL ","f":896.8,"g":0.0,"h":896.8},{"a":"10077475228","b":4995.47,"c":0.0,"d":4995.47,"e":"PEÑASALAZAR CESAR ANTONIO ","f":1534.0,"g":0.0,"h":1534.0},{"a":"09411119 ","b":3919.52,"c":0.0,"d":3919.52,"e":"PEVES ESQUIVEL FREDY ARTEMIO","f":1203.6,"g":0.0,"h":1203.6},{"a":"10404017859","b":9202.11,"c":1223.47,"d":7978.64,"e":"PERALTADURAN ROSARIO ELOIZA ","f":2832.0,"g":376.8,"h":2455.2},{"a":"46333606 ","b":8785.96,"c":0.0,"d":8785.96,"e":"PAUCAR JACOSANTOS ALBERTO ","f":2690.4,"g":0.0,"h":2690.4},{"a":"47133671 ","b":6301.97,"c":0.0,"d":6301.97,"e":"PAUCAR CASTRO KETTY PILAR ","f":1935.2,"g":0.0,"h":1935.2},{"a":"07464086 ","b":7270.81,"c":3134.32,"d":4136.49,"e":"PARILLO FLORESFLORA ","f":2218.4,"g":958.8,"h":1259.6},{"a":"46156804 ","b":6331.01,"c":0.0,"d":6331.01,"e":"PAREDES RAMOS VIOLETA GISELLA ","f":1935.2,"g":0.0,"h":1935.2},{"a":"09972307 ","b":3470.62,"c":0.0,"d":3470.62,"e":"PAREDESTAYPE CARMEN ROSARIO ","f":1062.0,"g":0.0,"h":1062.0},{"a":"20549769846","b":7712.48,"c":0.0,"d":7712.48,"e":"PAPIRO KIDS E.I.R.L.","f":2360.0,"g":0.0,"h":2360.0},{"a":"44834592 ","b":8946.49,"c":0.0,"d":8946.49,"e":"PANDURO MUÑOZ JULIA ELIZABETH ","f":2690.4,"g":0.0,"h":2690.4},{"a":"48325174 ","b":474.64,"c":0.0,"d":474.64,"e":"PALACIOS SOTOELIZABETH ROCIO","f":141.6,"g":0.0,"h":141.6},{"a":"10442729595","b":3024.06,"c":0.0,"d":3024.06,"e":"PAICO LLAMOGTANTAJHONNY ESTEVAN ","f":932.2,"g":0.0,"h":932.2},{"a":"44272959 ","b":6063.96,"c":0.0,"d":6063.96,"e":"PAICO LLAMOCTANTA JHONNY ESTEVAN","f":1864.4,"g":0.0,"h":1864.4},{"a":"10473256431","b":6176.25,"c":0.0,"d":6176.25,"e":"PACHECO BONILLA JOSIAS LEE","f":1899.8,"g":0.0,"h":1899.8},{"a":"48741642 ","b":3161.15,"c":0.0,"d":3161.15,"e":"PACHECO BONILLAMADAY LINA ","f":967.6,"g":0.0,"h":967.6},{"a":"10106330161","b":1531.17,"c":0.0,"d":1531.17,"e":"ORTIZ TRUJILLO NOEMI OMEGA","f":472.0,"g":0.0,"h":472.0},{"a":"10073536923","b":1722.56,"c":0.0,"d":1722.56,"e":"NUÑEZ QUISPE MARTHA ","f":531.0,"g":0.0,"h":531.0},{"a":"10459139163","b":3770.5,"c":0.0,"d":3770.5,"e":"NUÑEZROMAN DINA ","f":1162.3,"g":0.0,"h":1162.3},{"a":"20508142898","b":1859.02,"c":0.0,"d":1859.02,"e":"NOVEDADES ESTRELLA S.A.C. ","f":554.6,"g":0.0,"h":554.6},{"a":"41364298 ","b":6168.1,"c":0.0,"d":6168.1,"e":"NIÑO GUARNIZOOLGA ","f":1888.0,"g":0.0,"h":1888.0},{"a":"10449124605","b":1454.61,"c":0.0,"d":1454.61,"e":"NEYRA NUÑEZ MARTHA MIRTA","f":448.4,"g":0.0,"h":448.4},{"a":"20600895819","b":2414.18,"c":0.0,"d":2414.18,"e":"NERONY S.A.C. ","f":743.4,"g":0.0,"h":743.4},{"a":"20553961671","b":7305.24,"c":974.4,"d":6330.84,"e":"NEGOCIOS MAVER'SS S.A.C.","f":2242.0,"g":300.0,"h":1942.0},{"a":"07303782 ","b":1416.33,"c":0.0,"d":1416.33,"e":"MONDRAGONHUAMAN JOSE DOLORES","f":436.6,"g":0.0,"h":436.6},{"a":"15761955 ","b":766.41,"c":147.81,"d":618.6,"e":"MILLACHAVEZ YAQUELINE ISABEL","f":236.0,"g":45.5,"h":190.5},{"a":"09964030 ","b":5147.27,"c":0.0,"d":5147.27,"e":"MENAORTIZ PETER ","f":1535.58,"g":0.0,"h":1535.58},{"a":"20547627041","b":4598.46,"c":0.0,"d":4598.46,"e":"MELCHOR VEGA E.I.R.L. ","f":1416.0,"g":0.0,"h":1416.0},{"a":"10076171519","b":4473.23,"c":0.0,"d":4473.23,"e":"MAZA YANA VICTORIA","f":1368.8,"g":0.0,"h":1368.8},{"a":"20543426831","b":3483.41,"c":0.0,"d":3483.41,"e":"MARIBEL PRINCESS GIRLS S.A.C. ","f":1073.8,"g":0.0,"h":1073.8},{"a":"10447878203","b":2646.96,"c":0.0,"d":2646.96,"e":"MANOSALVA ORTIZ ELITA FLOR","f":814.2,"g":0.0,"h":814.2},{"a":"10073211871","b":2340.07,"c":0.0,"d":2340.07,"e":"MAMANIMAMANI BENANCIA ","f":719.8,"g":0.0,"h":719.8},{"a":"10445936851","b":2181.91,"c":0.0,"d":2181.91,"e":"MAMANICHAMBI YALID ELIZABETH","f":672.6,"g":0.0,"h":672.6},{"a":"10409208997","b":1913.96,"c":0.0,"d":1913.96,"e":"MAGALLANORTIZ VICTOR","f":590.0,"g":0.0,"h":590.0},{"a":"10096858600","b":16303.24,"c":9949.52,"d":6353.72,"e":"MACHACAGARCIA MARLENE ELIZABETH ","f":5015.0,"g":3068.0,"h":1947.0},{"a":"20552837372","b":5895.0,"c":0.0,"d":5895.0,"e":"LYLY LINO MONTALVO E.I.R.L. ","f":1817.2,"g":0.0,"h":1817.2},{"a":"10105796809","b":6694.97,"c":0.0,"d":6694.97,"e":"LUCANA POMA RENEE YURI","f":2053.2,"g":0.0,"h":2053.2},{"a":"10485110050","b":17003.45,"c":0.0,"d":17003.45,"e":"LOPEZ RODRIGUEZJULISA ERLINDA ","f":5215.6,"g":0.0,"h":5215.6},{"a":"44463792 ","b":1799.12,"c":0.0,"d":1799.12,"e":"LOPEZ PASCUAL CESAR ","f":554.6,"g":0.0,"h":554.6},{"a":"40922137 ","b":977.82,"c":0.0,"d":977.82,"e":"LOPEZANGELINO LISBETH YOHANA","f":300.9,"g":0.0,"h":300.9},{"a":"09655049 ","b":710.35,"c":0.0,"d":710.35,"e":"LIÑAN QUIÑONEZ JOHNNY NARSES","f":218.3,"g":0.0,"h":218.3},{"a":"41069683 ","b":1417.86,"c":0.0,"d":1417.86,"e":"LIVIA RAMOS WILDER NEXER","f":436.6,"g":0.0,"h":436.6},{"a":"42001970 ","b":7937.63,"c":0.0,"d":7937.63,"e":"LIVIA RAMOS EDGAR JUAN","f":2442.6,"g":0.0,"h":2442.6},{"a":"10441146359","b":25899.76,"c":14724.16,"d":11175.6,"e":"LIVIARAMOS LUS MARINA ","f":7920.0,"g":4498.0,"h":3422.0},{"a":"77693459 ","b":5766.48,"c":0.0,"d":5766.48,"e":"LEON CHUQUICHANCA ELIZABETH REBECA","f":1770.0,"g":0.0,"h":1770.0},{"a":"45025381 ","b":1823.31,"c":0.0,"d":1823.31,"e":"LENES GUISADO HAROL BETSY ","f":560.5,"g":0.0,"h":560.5},{"a":"76552380 ","b":11087.56,"c":162.35,"d":10925.21,"e":"LANDA COCA RAQUEL MARITZA ","f":3398.4,"g":50.0,"h":3348.4},{"a":"20508012765","b":8269.75,"c":0.0,"d":8269.75,"e":"KOSOAN S.A.C. ","f":2542.9,"g":0.0,"h":2542.9},{"a":"20557971701","b":5327.31,"c":0.0,"d":5327.31,"e":"JUSMAREM E.I.R.L. ","f":1628.4,"g":0.0,"h":1628.4},{"a":"46765473 ","b":11.4,"c":0.0,"d":11.4,"e":"JULCA ARIASJHOEL JUANJHO","f":3.4,"g":0.0,"h":3.4},{"a":"20508212349","b":10026.22,"c":5.84,"d":10020.38,"e":"JOISCA S.A.C. ","f":3068.0,"g":1.8,"h":3066.2},{"a":"20555302381","b":30331.79,"c":4004.96,"d":26326.83,"e":"JM & VP IMPORTADORA S.A.C.","f":9204.0,"g":1231.0,"h":7973.0},{"a":"10410659307","b":15115.72,"c":0.0,"d":15115.72,"e":"JAUREGUISOTELO SOLEDAD","f":4602.0,"g":0.0,"h":4602.0},{"a":"42584259 ","b":6327.11,"c":0.0,"d":6327.11,"e":"IZARRA TINOCO GERARDA ISABEL","f":1947.0,"g":0.0,"h":1947.0},{"a":"20600051246","b":2647.78,"c":0.0,"d":2647.78,"e":"INVERSIONES VALENTINA MC S.A.C. ","f":814.2,"g":0.0,"h":814.2},{"a":"20523210263","b":15342.83,"c":0.0,"d":15342.83,"e":"INVERSIONES STUDIO V Y V E.I.R.L. ","f":4720.0,"g":0.0,"h":4720.0},{"a":"20517223027","b":6215.19,"c":0.0,"d":6215.19,"e":"INVERSIONES A & R HNOS S.A.C. ","f":1899.8,"g":0.0,"h":1899.8},{"a":"20451736079","b":3827.92,"c":0.0,"d":3827.92,"e":"INVERSIONES & CONFECCIONES S.R.L. ","f":1180.0,"g":0.0,"h":1180.0},{"a":"20190687571","b":1028.39,"c":0.0,"d":1028.39,"e":"IMPORTADORA ORIENTAL E.I.R.L. ","f":306.8,"g":0.0,"h":306.8},{"a":"10561053 ","b":5944.97,"c":0.0,"d":5944.97,"e":"HUAYLLASCO MOTTAALEX","f":1817.2,"g":0.0,"h":1817.2},{"a":"44492228 ","b":13636.39,"c":0.0,"d":13636.39,"e":"HUAMANI NUÑEZINES ROXANA","f":4068.13,"g":0.0,"h":4068.13},{"a":"47192057 ","b":3322.5,"c":0.0,"d":3322.5,"e":"HUAMAN ORTIZGLADIS","f":991.2,"g":0.0,"h":991.2},{"a":"10080117944","b":15645.19,"c":0.0,"d":15645.19,"e":"HERRERA ZULOAGATEODULO FELIX","f":4814.4,"g":0.0,"h":4814.4},{"a":"10736318178","b":3163.08,"c":0.0,"d":3163.08,"e":"HERNANDEZ GARAY DIANA LIZETH","f":967.6,"g":0.0,"h":967.6},{"a":"71822637 ","b":791.07,"c":0.0,"d":791.07,"e":"GUIVAR MARTINEZLUCELINA ","f":236.0,"g":0.0,"h":236.0},{"a":"10803778952","b":5837.58,"c":0.0,"d":5837.58,"e":"GOMEZMARQUEZ LUCIA KAREN","f":1799.5,"g":0.0,"h":1799.5},{"a":"20517295010","b":5014.64,"c":0.0,"d":5014.64,"e":"GIOCARYD S.A.C. ","f":1534.0,"g":0.0,"h":1534.0},{"a":"10132247 ","b":3065.64,"c":0.0,"d":3065.64,"e":"GERONIMO JUNESLILIANA IVONE ","f":944.0,"g":0.0,"h":944.0},{"a":"08919440 ","b":2299.23,"c":0.0,"d":2299.23,"e":"GARCIA ESPINOZAZOILA FELICITA ","f":708.0,"g":0.0,"h":708.0},{"a":"74071564 ","b":3163.08,"c":0.0,"d":3163.08,"e":"GARAY RAZO NICHOLLE JESUS ","f":967.6,"g":0.0,"h":967.6},{"a":"10097327420","b":3471.68,"c":0.0,"d":3471.68,"e":"GARAYNOEL ANGELINA ZOILA","f":1062.0,"g":0.0,"h":1062.0},{"a":"10101017571","b":2488.15,"c":0.0,"d":2488.15,"e":"GAMARRA MONTESINOS SILVIA ","f":767.0,"g":0.0,"h":767.0},{"a":"06201480 ","b":5464.31,"c":0.0,"d":5464.31,"e":"GALVEZ RUIZ VILMA MARISSA ","f":1681.5,"g":0.0,"h":1681.5},{"a":"20508076143","b":881.24,"c":0.0,"d":881.24,"e":"GALENICA SOLUCIONES S.A.C.","f":271.4,"g":0.0,"h":271.4},{"a":"20521722259","b":3915.31,"c":0.0,"d":3915.31,"e":"GABRIATEX S.A.C.","f":1203.6,"g":0.0,"h":1203.6},{"a":"20551687172","b":1324.36,"c":1310.16,"d":14.2,"e":"G&R GIOROX COMPANY S.A.C. ","f":401.2,"g":401.2,"h":0.0},{"a":"10724474999","b":6537.83,"c":0.0,"d":6537.83,"e":"FONSECA OCHOA NOEMI YISELA","f":2006.0,"g":0.0,"h":2006.0},{"a":"33826025 ","b":2685.33,"c":0.0,"d":2685.33,"e":"FERROÑANVIERA MIRTHA SOLEDAD","f":826.0,"g":0.0,"h":826.0},{"a":"74034832 ","b":2109.9,"c":0.0,"d":2109.9,"e":"FERNANDEZ LAYME LUIS MANUEL ","f":649.0,"g":0.0,"h":649.0},{"a":"10442964373","b":1880.88,"c":0.0,"d":1880.88,"e":"FERNANDEZMORALES MARILU GRACIELA","f":578.2,"g":0.0,"h":578.2},{"a":"10062178073","b":2608.6,"c":0.0,"d":2608.6,"e":"FALCON CABRERA RAQUEL CONCEPCION","f":802.4,"g":0.0,"h":802.4},{"a":"44858464 ","b":3335.17,"c":0.0,"d":3335.17,"e":"FABIAN VERAANA RUTH ","f":994.98,"g":0.0,"h":994.98},{"a":"10097635396","b":1669.77,"c":0.0,"d":1669.77,"e":"ESTRELLAROSALES HORTENCIA ","f":513.3,"g":0.0,"h":513.3},{"a":"44053464 ","b":4020.43,"c":0.0,"d":4020.43,"e":"ESTEBA JACOVERONICA ","f":1199.41,"g":0.0,"h":1199.41},{"a":"09597684 ","b":10698.56,"c":0.0,"d":10698.56,"e":"ESPINOZA LARALUIS ALBERTO ","f":3292.2,"g":0.0,"h":3292.2},{"a":"42541975 ","b":4309.41,"c":1088.34,"d":3221.07,"e":"ESCOBEDO CABALLERO PAYMER LEONEL","f":1321.6,"g":330.4,"h":991.2},{"a":"06201288 ","b":29240.97,"c":0.0,"d":29240.97,"e":"ESCANDONBORJA JOSE","f":8723.44,"g":0.0,"h":8723.44},{"a":"20551117660","b":3402.54,"c":2391.87,"d":1010.67,"e":"ENTERPRISE LUANA COLLECTION S.R.L.","f":1015.08,"g":767.0,"h":248.08},{"a":"20106897914","b":9189.39,"c":9098.66,"d":90.73,"e":"ENTEL PERU S.A. ","f":2802.5,"g":2803.89,"h":-1.39},{"a":"20543187071","b":5440.51,"c":0.0,"d":5440.51,"e":"EMPORIUM MATO DESIGN S.R.L. ","f":1675.6,"g":0.0,"h":1675.6},{"a":"10092029978","b":4918.62,"c":0.0,"d":4918.62,"e":"DIAZFERNANDEZ DE FERNANDEZ MARIA ELVA ","f":1510.4,"g":0.0,"h":1510.4},{"a":"44211659 ","b":44.25,"c":0.0,"d":44.25,"e":"DELGADO PACHECOKATY ","f":13.2,"g":0.0,"h":13.2},{"a":"20393020807","b":3008.79,"c":0.0,"d":3008.79,"e":"DEBORHA'S E.I.R.L ","f":920.4,"g":0.0,"h":920.4},{"a":"20600283295","b":20819.66,"c":39.61,"d":20780.05,"e":"DAYANNA CONFECCIONES E.I.R.L. ","f":6407.4,"g":12.2,"h":6395.2},{"a":"10459537797","b":14696.49,"c":0.0,"d":14696.49,"e":"DAVILA ALVA HERMILINDA","f":4507.6,"g":0.0,"h":4507.6},{"a":"09096851 ","b":3458.4,"c":0.0,"d":3458.4,"e":"CURI MORALES CONSUELO ","f":1062.0,"g":0.0,"h":1062.0},{"a":"41124993 ","b":593.33,"c":0.0,"d":593.33,"e":"CUADROS LOPEZ ALFREDO ","f":182.9,"g":0.0,"h":182.9},{"a":"20601614473","b":3717.09,"c":0.0,"d":3717.09,"e":"CREACIONES JESSILU EIRL ","f":1144.6,"g":0.0,"h":1144.6},{"a":"20518043171","b":11341.13,"c":0.0,"d":11341.13,"e":"CORPORACION MELIKAR E.I.R.L.","f":3492.8,"g":0.0,"h":3492.8},{"a":"20551123635","b":10151.55,"c":3422.92,"d":6728.63,"e":"CORPORACION LDS S.A.C.","f":3097.5,"g":1032.5,"h":2065.0},{"a":"20546710671","b":5741.88,"c":575.07,"d":5166.81,"e":"CORPORACION GAMEL S.A.C.","f":1770.0,"g":177.0,"h":1593.0},{"a":"47835461 ","b":17973.53,"c":0.0,"d":17973.53,"e":"CORONADO SANDOVAL KARI DALINA ","f":5522.4,"g":0.0,"h":5522.4},{"a":"48720204 ","b":4067.96,"c":0.0,"d":4067.96,"e":"CORONADO CORNELIO STEFANI CAROLINA","f":1250.8,"g":0.0,"h":1250.8},{"a":"47531260 ","b":6941.23,"c":0.0,"d":6941.23,"e":"CORONADO CORNELIO ANA MILAGROS","f":2124.0,"g":0.0,"h":2124.0},{"a":"20552397976","b":3065.64,"c":0.0,"d":3065.64,"e":"CONSORCIO TEXTIL TKC S.A.C. ","f":944.0,"g":0.0,"h":944.0},{"a":"20518923642","b":5512.2,"c":0.0,"d":5512.2,"e":"COMERCIAL TEXTIL DULCE SUEÑOS S.A.C.","f":1699.2,"g":0.0,"h":1699.2},{"a":"20544549538","b":11292.36,"c":0.0,"d":11292.36,"e":"COLLECTION J & S E.I.R.L. ","f":3481.0,"g":0.0,"h":3481.0},{"a":"10068136330","b":54306.24,"c":0.0,"d":54306.24,"e":"CISNEROS CARDENASPAULINO","f":16614.4,"g":0.0,"h":16614.4},{"a":"71854996 ","b":1967.29,"c":0.0,"d":1967.29,"e":"CIEZA CERCADO HENRRY ESNEIDER ","f":601.8,"g":0.0,"h":601.8},{"a":"20556761605","b":1569.45,"c":0.0,"d":1569.45,"e":"CHIVY'S S.A.C.","f":483.8,"g":0.0,"h":483.8},{"a":"10641440 ","b":2985.78,"c":0.0,"d":2985.78,"e":"CHIQUILLAN ANCCO FRANCISCO","f":920.4,"g":0.0,"h":920.4},{"a":"47827760 ","b":1031.95,"c":0.0,"d":1031.95,"e":"CHERRES QUEREBALUNANCY DEL PILAR","f":307.86,"g":0.0,"h":307.86},{"a":"10426957910","b":4392.98,"c":0.0,"d":4392.98,"e":"CHAVEZCORNEJO PATRICIA","f":1345.2,"g":0.0,"h":1345.2},{"a":"44837354 ","b":19917.81,"c":2574.31,"d":17343.5,"e":"CHAMBILLALLANOS FREDY ","f":6053.4,"g":787.95,"h":5265.45},{"a":"10094628682","b":4905.03,"c":0.0,"d":4905.03,"e":"CHAMBICAYO JAIME BAILON ","f":1510.4,"g":0.0,"h":1510.4},{"a":"42325502 ","b":1072.81,"c":0.0,"d":1072.81,"e":"CERNA ACUÑA CARMEN ROSA ","f":330.4,"g":0.0,"h":330.4},{"a":"20501655580","b":91031.72,"c":0.0,"d":91031.72,"e":"CENTRO GAMARRA S.A.C","f":27953.12,"g":0.0,"h":27953.12},{"a":"10448438061","b":11935.5,"c":0.0,"d":11935.5,"e":"CECENARROCANAZA MARCOS","f":3669.8,"g":0.0,"h":3669.8},{"a":"45642341 ","b":1342.66,"c":0.0,"d":1342.66,"e":"CCANTO MAYTA RICHARD EDUARDO","f":413.0,"g":0.0,"h":413.0},{"a":"09325659 ","b":1475.12,"c":0.0,"d":1475.12,"e":"CAÑAPATAÑA TICONA BETTY BENITA","f":454.3,"g":0.0,"h":454.3},{"a":"10423534 ","b":8430.51,"c":0.0,"d":8430.51,"e":"CASTRO MENDOZAMARIA ","f":2596.0,"g":0.0,"h":2596.0},{"a":"42093029 ","b":2264.74,"c":0.0,"d":2264.74,"e":"CASTRO LIMAYLLA LUZ VERONICA","f":696.2,"g":0.0,"h":696.2},{"a":"10104648636","b":3260.75,"c":0.0,"d":3260.75,"e":"CASTROJESUS NORMA DOMINICA","f":1003.0,"g":0.0,"h":1003.0},{"a":"10060440692","b":6700.27,"c":0.0,"d":6700.27,"e":"CASTILLO FEIJO DE CANALES CARMEN AUDULIA","f":2053.2,"g":0.0,"h":2053.2},{"a":"07344713 ","b":2610.54,"c":741.19,"d":1869.35,"e":"CASTAÑEDA ROSALES DE MERCADODALIA CARMEN","f":778.8,"g":220.2,"h":558.6},{"a":"10073464019","b":4350.9,"c":821.24,"d":3529.66,"e":"CASSANA FLORESAMPARO ROSSANA","f":1298.0,"g":250.99,"h":1047.01},{"a":"10413294211","b":5052.85,"c":0.65,"d":5052.2,"e":"CASIMIRO SIERRA SENDY JANET ","f":1557.6,"g":0.2,"h":1557.4},{"a":"45150217 ","b":4598.46,"c":0.0,"d":4598.46,"e":"CARHUAYO SALAS MILAGROS ","f":1416.0,"g":0.0,"h":1416.0},{"a":"10586422 ","b":18943.5,"c":1514.45,"d":17429.05,"e":"CARDENAS MARTINEZ RAUL","f":5740.7,"g":459.7,"h":5281.0},{"a":"10106070941","b":11785.65,"c":0.0,"d":11785.65,"e":"CARDENAS MARTINEZROCILDA","f":3610.8,"g":0.0,"h":3610.8},{"a":"10072588954","b":15328.17,"c":908.28,"d":14419.89,"e":"CARDENASMARTINEZ ARMANDINA","f":4661.0,"g":279.62,"h":4381.38},{"a":"10434811975","b":3528.05,"c":98.7,"d":3429.35,"e":"CANCINO ESPANTOSO YNGRIT KAREN","f":1052.52,"g":30.0,"h":1022.52},{"a":"10402049958","b":3548.83,"c":0.0,"d":3548.83,"e":"CACERESVALDIVIEZO ANA ELIZABETH ","f":1085.6,"g":0.0,"h":1085.6},{"a":"44122122 ","b":1582.14,"c":0.0,"d":1582.14,"e":"BOZA CRUZWENDY YACKELING","f":472.0,"g":0.0,"h":472.0},{"a":"20555146401","b":6473.6,"c":0.0,"d":6473.6,"e":"BELLISIMAZ EXCLUSIVE S.A.C. ","f":1994.2,"g":0.0,"h":1994.2},{"a":"46890461 ","b":1550.3,"c":0.0,"d":1550.3,"e":"BELLIDO QUICAÑO JHON MILTON ","f":477.9,"g":0.0,"h":477.9},{"a":"15860566 ","b":2069.31,"c":0.0,"d":2069.31,"e":"BAZALAR SALAVARRIA JOSE ANTONIO ","f":637.2,"g":0.0,"h":637.2},{"a":"40612814 ","b":2220.19,"c":0.0,"d":2220.19,"e":"BAUTISTA CALDERON JORGE ALBERTO ","f":684.4,"g":0.0,"h":684.4},{"a":"44208338 ","b":1918.09,"c":0.0,"d":1918.09,"e":"BAUTISTA CALDERON JEANETTE JACKELYN ","f":590.0,"g":0.0,"h":590.0},{"a":"46122413 ","b":1764.64,"c":0.0,"d":1764.64,"e":"BAUTISTA CALDERON DIANA CAROLINA","f":542.8,"g":0.0,"h":542.8},{"a":"10420347770","b":1779.98,"c":0.0,"d":1779.98,"e":"BANCES RAMOSMARIA ANGELICA","f":548.7,"g":0.0,"h":548.7},{"a":"10349085 ","b":4402.11,"c":0.0,"d":4402.11,"e":"ARROYONAOLA ROSARIO ","f":1357.0,"g":0.0,"h":1357.0},{"a":"07530796 ","b":4214.61,"c":0.0,"d":4214.61,"e":"ARIAS ESPINOZA SARA MILAGROS","f":1298.0,"g":0.0,"h":1298.0},{"a":"10430713316","b":1879.73,"c":0.0,"d":1879.73,"e":"ARAPAMAMANI CHRISTIAN CHARLES ","f":578.2,"g":0.0,"h":578.2},{"a":"44255352 ","b":2781.24,"c":0.0,"d":2781.24,"e":"ALVARADOGUZMAN ANGELA AMPARO","f":855.5,"g":0.0,"h":855.5},{"a":"07149433 ","b":6066.46,"c":0.0,"d":6066.46,"e":"ALCANTARACASASOLA JUANA MARIA ","f":1809.8,"g":0.0,"h":1809.8},{"a":"10484515846","b":8098.1,"c":0.0,"d":8098.1,"e":"ALBA MARIN MAGALY BRIGITH ","f":2478.0,"g":0.0,"h":2478.0},{"a":"10231471508","b":1837.4,"c":0.0,"d":1837.4,"e":"ACOSTA VALDIVIEZO CANDELARIA CARMEN ","f":566.4,"g":0.0,"h":566.4}]}
