{"data":[{"a":"20486196069","b":298.6,"c":12.0,"d":286.6,"e":"TRANSPORTES Y SERVICIOS GIN-MIR. E.I.R.L. "},{"a":"10434737694","b":1210.07,"c":1250.4,"d":-40.33,"e":"RIVERA PALOMINO BLANCA NIEVES "},{"a":"20486439492","b":290.28,"c":298.7,"d":-8.42,"e":"REPUESTOS Y SERVICIOS JAPAN PARTES S.C.R.L. "},{"a":"10198965036","b":715.18,"c":735.91,"d":-20.73,"e":"MENDOZA GALLARDO MIDIAN EUGENIA "},{"a":"20568728255","b":338.45,"c":348.26,"d":-9.81,"e":"IMPORTACIONES E INVERSIONES GENERALES DACL SAC"},{"a":"10414309882","b":1671.71,"c":1688.86,"d":-17.15,"e":"HINOSTROZA CUADROS MERCEDES ODELINDA"},{"a":"20443848178","b":132.0,"c":20.0,"d":112.0,"e":"EMP DE TRANSPORTES TICLLAS SAC"},{"a":"20486115832","b":307.62,"c":0.0,"d":307.62,"e":" EMPRESA DE TRANSPORTES VIATRANS E.I.R.L. "}]}
