{"0":[],"1":[{"a":"1411","b":0.0,"c":70.0,"d":0.0,"e":70.0},{"a":"1411","b":0.0,"c":1000.0,"d":0.0,"e":1000.0},{"a":"1411","b":0.0,"c":660.0,"d":0.0,"e":660.0}],"2":[{"a":"1411","b":333.0,"c":0.0,"d":333.0,"e":0.0},{"a":"1411","b":23.0,"c":0.0,"d":23.0,"e":0.0},{"a":"1411","b":220.0,"c":0.0,"d":220.0,"e":0.0},{"a":"1411","b":23.0,"c":0.0,"d":6.53,"e":0.0},{"a":"1411","b":333.0,"c":0.0,"d":94.6,"e":0.0},{"a":"1411","b":220.0,"c":0.0,"d":62.5,"e":0.0}],"3":[{"a":"1411","b":334.0,"c":0.0,"d":95.7,"e":0.0},{"a":"1411","b":24.0,"c":0.0,"d":6.88,"e":0.0},{"a":"1411","b":220.0,"c":0.0,"d":63.04,"e":0.0},{"a":"1411","b":0.0,"c":1000.0,"d":0.0,"e":1000.0}],"4":[],"5":[{"a":"1411","b":250.0,"c":0.0,"d":74.85,"e":0.0},{"a":"1411","b":250.0,"c":0.0,"d":74.63,"e":0.0}],"6":[{"a":"1411","b":250.0,"c":0.0,"d":74.63,"e":0.0},{"a":"1411","b":0.0,"c":1388.0,"d":0.0,"e":1388.0},{"a":"1411","b":0.0,"c":2.0,"d":0.0,"e":2.0},{"a":"1411","b":0.0,"c":608.4,"d":0.0,"e":608.4},{"a":"1411","b":0.0,"c":478.5,"d":0.0,"e":478.5},{"a":"1411","b":0.0,"c":413.1,"d":0.0,"e":413.1},{"a":"1612","b":0.0,"c":869.8,"d":0.0,"e":869.8}],"7":[{"a":"1612","b":869.8,"c":0.0,"d":869.8,"e":0.0},{"a":"1411","b":21.5,"c":0.0,"d":6.5,"e":0.0},{"a":"1411","b":478.5,"c":0.0,"d":144.56,"e":0.0},{"a":"1411","b":1390.0,"c":0.0,"d":419.94,"e":0.0},{"a":"1411","b":250.0,"c":0.0,"d":75.53,"e":0.0}],"8":[{"a":"1411","b":300.0,"c":0.0,"d":89.82,"e":0.0},{"a":"1411","b":0.0,"c":500.0,"d":0.0,"e":500.0},{"a":"1411","b":0.0,"c":500.0,"d":0.0,"e":500.0}],"9":[{"a":"1411","b":300.0,"c":0.0,"d":88.24,"e":0.0},{"a":"1411","b":167.0,"c":0.0,"d":48.69,"e":0.0},{"a":"1411","b":167.0,"c":0.0,"d":48.69,"e":0.0},{"a":"1411","b":0.0,"c":136.0,"d":0.0,"e":136.0}],"10":[{"a":"1411","b":136.0,"c":0.0,"d":39.77,"e":0.0},{"a":"1411","b":300.0,"c":0.0,"d":87.72,"e":0.0},{"a":"1411","b":167.0,"c":0.0,"d":48.69,"e":0.0},{"a":"1411","b":167.0,"c":0.0,"d":48.69,"e":0.0}],"11":[{"a":"1411","b":100.0,"c":0.0,"d":29.03,"e":0.0},{"a":"1411","b":166.0,"c":0.0,"d":48.19,"e":0.0},{"a":"1411","b":166.0,"c":0.0,"d":48.19,"e":0.0}],"12":[],"13":[]}
