{"0":[],"1":[{"a":1731.53}],"2":[{"a":266.1},{"a":431.36}],"3":[{"a":20.34}],"4":[{"a":1884.24},{"a":7475.42}],"5":[{"a":11.86},{"a":1925.35},{"a":118.64}],"6":[{"a":6.78},{"a":0.0},{"a":5.93},{"a":19.49},{"a":11.86},{"a":220.34},{"a":0.0},{"a":0.0},{"a":0.0}],"7":[{"a":8.47},{"a":8.47}],"8":[{"a":432.2},{"a":8.47},{"a":8.48},{"a":5.93},{"a":16.95},{"a":56.44},{"a":5223.0},{"a":1706.19},{"a":590.1}],"9":[{"a":27.12}],"10":[{"a":4.24},{"a":213.98},{"a":2791.15}],"11":[{"a":5.93},{"a":494.92},{"a":3.39},{"a":1576.38}],"12":[{"a":115.25}]}
