{"data":[{"a":"42087681 ","b":0.0,"c":2041.96,"d":2041.96,"e":"ZURITA YBAZETA GIANIRA KATTIUSKA"},{"a":"44100461 ","b":0.0,"c":714.5,"d":714.5,"e":"ZAVALA AYVAR ROBERTO SANTOS "},{"a":"40638579 ","b":0.0,"c":778.65,"d":778.65,"e":"ZARSOZA SOLIS ALFREDO WILVER"},{"a":"44793360 ","b":0.0,"c":915.15,"d":915.15,"e":"YOPLA MURRUGARRA ROCIO CASIMIRA "},{"a":"46383543 ","b":0.0,"c":783.84,"d":783.84,"e":"YARANGA YARANGA YOEL JHONATAN "},{"a":"42559402 ","b":0.0,"c":1999.9,"d":1999.9,"e":"YARANGA DE LA CRUZ ELVIS AUGUSTO"},{"a":"46630123 ","b":0.0,"c":898.96,"d":898.96,"e":"VIVANCO MEDINA YENIFER ESTEFANI "},{"a":"40243239 ","b":0.0,"c":2580.94,"d":2580.94,"e":"VILCAHUAMAN QUISPE MICHAEL NEIL "},{"a":"42887053 ","b":0.0,"c":1830.97,"d":1830.97,"e":"VERASTEGUI VALDERRAMA ANDREA CECILIA"},{"a":"06988132 ","b":0.0,"c":977.77,"d":977.77,"e":"VERA VEGA GILMER GUSTAVO"},{"a":"10142453 ","b":0.0,"c":717.75,"d":717.75,"e":"VERA SALAS ERICH EDUARDO"},{"a":"48221479 ","b":0.0,"c":841.09,"d":841.09,"e":"VELASQUEZ RAMON, XIOMARA DANIXA "},{"a":"46980522 ","b":0.0,"c":783.0,"d":783.0,"e":"VEGA LOPEZ LUIS KENIDI"},{"a":"74569617 ","b":0.0,"c":522.0,"d":522.0,"e":"VASQUEZ AGUILAR JOSE BAINER "},{"a":"42405014 ","b":0.0,"c":941.98,"d":941.98,"e":"VALENZUELA TIMOTEO YESENIA SHEYLA "},{"a":"41468954 ","b":0.0,"c":1638.99,"d":1638.99,"e":"TUMBAJULCA CRUZADO WILLIAM MIGUEL "},{"a":"43064201 ","b":0.0,"c":782.22,"d":782.22,"e":"TUMBAJULCA CRUZADO JORGE LUIS "},{"a":"45573610 ","b":0.0,"c":308.39,"d":308.39,"e":"TORRES BALBOA, PERCY IVAN "},{"a":"000804803","b":0.0,"c":1279.05,"d":1279.05,"e":"TORO MONTOYA YADIRA "},{"a":"47410907 ","b":0.0,"c":823.59,"d":823.59,"e":"TIPISMANA CHAVEZ WILLIAM JESUS"},{"a":"48503178 ","b":0.0,"c":783.0,"d":783.0,"e":"TINEO SERNA WILDER FIDEL"},{"a":"46177190 ","b":0.0,"c":1140.29,"d":1140.29,"e":"TICSE QUINTANILLA GABRIEL GEDEON"},{"a":"43203600 ","b":0.0,"c":823.59,"d":823.59,"e":"TELLO BAZAN FREDY "},{"a":"44234452 ","b":0.0,"c":2161.64,"d":2161.64,"e":"TAGLE PACHERREZ JONATHAN"},{"a":"46261770 ","b":0.0,"c":888.35,"d":888.35,"e":"SULCARAY SOTELO MELISSA "},{"a":"46694199 ","b":0.0,"c":1206.42,"d":1206.42,"e":"SULCA GAMARRA GERARDO ENRIQUE "},{"a":"45816682 ","b":0.0,"c":793.92,"d":793.92,"e":"SOTELO JARA VICENTE "},{"a":"46837131 ","b":0.0,"c":1131.19,"d":1131.19,"e":"SOLIS MORAN DICKS DONOVAN "},{"a":"10397078 ","b":0.0,"c":805.25,"d":805.25,"e":"SOLANO QUISPE JOSE ANGEL"},{"a":"80609809 ","b":0.0,"c":1203.67,"d":1203.67,"e":"SOLANO QUISPE JOHN ALEXANDER"},{"a":"46722472 ","b":0.0,"c":740.32,"d":740.32,"e":"SILVERA RUIZ FABIOLA REGINA "},{"a":"42924466 ","b":0.0,"c":1034.6,"d":1034.6,"e":"SILVA CHURA ORLANDO "},{"a":"001018583","b":0.0,"c":839.03,"d":839.03,"e":"SEGOVIA CAMPO JAIME ALBERTO "},{"a":"42847587 ","b":0.0,"c":261.0,"d":261.0,"e":"SARMIENTO ROCA FRANK"},{"a":"80174820 ","b":0.0,"c":1280.39,"d":1280.39,"e":"SARA IPARRAGUIRRE JANET CARMEN"},{"a":"47831878 ","b":0.0,"c":526.72,"d":526.72,"e":"SANTOS ANAYA, BRUCE BRYAN "},{"a":"20114850 ","b":0.0,"c":1280.44,"d":1280.44,"e":"SANTIANI CARHUAS ISABEL MARCEL"},{"a":"44848067 ","b":0.0,"c":1141.51,"d":1141.51,"e":"SANTIAGO ZACONETA WILBER HUMBERTO "},{"a":"43142627 ","b":0.0,"c":1218.29,"d":1218.29,"e":"SANTIAGO AQUIÑO HERLISS JOHONATAN "},{"a":"41189814 ","b":0.0,"c":1248.38,"d":1248.38,"e":"SANDOVAL PAREDES CARLA MARIA"},{"a":"10518178 ","b":0.0,"c":780.59,"d":780.59,"e":"SANCHEZ MEDINA RODOLFO WILLIAM"},{"a":"43699616 ","b":0.0,"c":1545.53,"d":1545.53,"e":"SALAZAR MONTERO ELVIS "},{"a":"46725130 ","b":0.0,"c":497.32,"d":497.32,"e":"SALAS CORREA ALESHA "},{"a":"09146258 ","b":0.0,"c":1843.07,"d":1843.07,"e":"RUPIRI CHECCNES LEONARDO SEVERO "},{"a":"46415048 ","b":0.0,"c":678.65,"d":678.65,"e":"RUIZ GARCIA SILVIA MASSIEL"},{"a":"10430366 ","b":0.0,"c":1965.24,"d":1965.24,"e":"ROMERO QUIROZ STEVE FRANCISCO "},{"a":"000833722","b":0.0,"c":1591.67,"d":1591.67,"e":"RIVADENEIRA SALDARRIAGA MANUEL ANDRES "},{"a":"40605181 ","b":0.0,"c":1005.69,"d":1005.69,"e":"RIOS ESTERRIPA JOSE ANTONIO "},{"a":"42147620 ","b":0.0,"c":883.0,"d":883.0,"e":"RICRA RIVAS FLOREANO"},{"a":"43645341 ","b":0.0,"c":783.0,"d":783.0,"e":"REYNALDE GASPAR KEMPES"},{"a":"72679684 ","b":0.0,"c":783.0,"d":783.0,"e":"REYES CARRANZA, SLIND MERCEDES"},{"a":"001101012","b":0.0,"c":434.75,"d":434.75,"e":"REY GUALTERO PAOLA MARCELA"},{"a":"001125844","b":0.0,"c":434.94,"d":434.94,"e":"RENDON HERRERA JUAN CARLOS"},{"a":"43053282 ","b":0.0,"c":783.48,"d":783.48,"e":"REATEGUI PORTUGAL JEAN POOL "},{"a":"42693528 ","b":0.0,"c":433.16,"d":433.16,"e":"REA CHUCHON HENRY "},{"a":"45668791 ","b":0.0,"c":823.59,"d":823.59,"e":"RAMOS CCOYCCA DAVID MOISES"},{"a":"46667349 ","b":0.0,"c":1071.63,"d":1071.63,"e":"RAMON CORDOVA, MARISOL AIDA "},{"a":"25849570 ","b":0.0,"c":776.1,"d":776.1,"e":"RAMIREZ VASQUEZ EDWIN ELADIO"},{"a":"001077314","b":0.0,"c":573.31,"d":573.31,"e":"RAMIREZ CARDONA SANDRA MILENA "},{"a":"44194480 ","b":0.0,"c":823.03,"d":823.03,"e":"QUISPE USCACHI WALTER FRANCISCO "},{"a":"28271442 ","b":0.0,"c":905.66,"d":905.66,"e":"QUISPE TORRES ANTONIO "},{"a":"42727675 ","b":0.0,"c":1133.97,"d":1133.97,"e":"QUISPE PARIONA MIGUEL ANGEL "},{"a":"47263920 ","b":0.0,"c":678.63,"d":678.63,"e":"QUISPE MAGALLANES, BRENDA LUZ "},{"a":"46029393 ","b":0.0,"c":1486.79,"d":1486.79,"e":"QUISPE LOPEZ CHIRSTIAN VLADIMIR "},{"a":"10028245 ","b":0.0,"c":822.15,"d":822.15,"e":"QUISPE LAYME ELEUTERIO"},{"a":"40785032 ","b":0.0,"c":1054.34,"d":1054.34,"e":"QUISPE ASTUPIÑAN GUIULEANO RICARDO"},{"a":"45118573 ","b":0.0,"c":1250.03,"d":1250.03,"e":"QUIROZ NAVARRETE FERNANDO EDWARD"},{"a":"40448109 ","b":0.0,"c":822.15,"d":822.15,"e":"QUINTANILLA CHUQUILLANQUI JOSE ANTONIO"},{"a":"44213731 ","b":0.0,"c":822.15,"d":822.15,"e":"QUEZADA TORRES DIANA CAROLINA "},{"a":"10726203 ","b":0.0,"c":822.65,"d":822.65,"e":"QUEVEDO CHAVARRI, FREDDY JIMMY"},{"a":"42688391 ","b":0.0,"c":751.38,"d":751.38,"e":"QUESQUEN PEREZ LUIS ALEXANDER "},{"a":"47545060 ","b":0.0,"c":794.15,"d":794.15,"e":"PUENTE ZARATE GABRIEL "},{"a":"46675100 ","b":0.0,"c":666.26,"d":666.26,"e":"PUELLES MENDEZ LUIS ALBERTO "},{"a":"40780996 ","b":0.0,"c":1249.13,"d":1249.13,"e":"PRADO WALDE ALAN EDWIN"},{"a":"44426457 ","b":0.0,"c":674.22,"d":674.22,"e":"POTENCIANO MANRIQUE INES GENOVEVA "},{"a":"10750703 ","b":0.0,"c":832.86,"d":832.86,"e":"PORTILLO ALCANTARA JHON ALEX"},{"a":"08009098 ","b":0.0,"c":757.02,"d":757.02,"e":"PORTILLA TABARNE LUIS ARMANDO "},{"a":"46457330 ","b":0.0,"c":1034.64,"d":1034.64,"e":"PONCE QUESQUEN LUIS ARTURO"},{"a":"45076827 ","b":0.0,"c":940.61,"d":940.61,"e":"PIEDRA ESCURRA JAVIER DANIEL"},{"a":"46729230 ","b":0.0,"c":626.4,"d":626.4,"e":"PEÑA CHINCHAY HINMER"},{"a":"80320323 ","b":0.0,"c":1555.03,"d":1555.03,"e":"PEREZ REYES JUAN PABLO"},{"a":"44797829 ","b":0.0,"c":1086.11,"d":1086.11,"e":"PEREZ APESTEGUI WILLIAN JESUS "},{"a":"46301968 ","b":0.0,"c":582.22,"d":582.22,"e":"PEREZ ALCANTARA CINDY VANESA"},{"a":"43202908 ","b":0.0,"c":2217.25,"d":2217.25,"e":"PEREA MEDINA CESAR DANIEL "},{"a":"001169727","b":0.0,"c":351.64,"d":351.64,"e":"PENBERTY LEYDI JULIANA"},{"a":"41949995 ","b":0.0,"c":391.73,"d":391.73,"e":"PATALA VASQUEZ TOMAS JONATHAN "},{"a":"46377125 ","b":0.0,"c":794.86,"d":794.86,"e":"PARIONA YARANGA EZLIN "},{"a":"46941025 ","b":0.0,"c":1007.96,"d":1007.96,"e":"PARIONA NUÑEZ ELMER DAVID "},{"a":"41004713 ","b":0.0,"c":1085.39,"d":1085.39,"e":"PAREDES VALIENTE LUIS ALBERTO "},{"a":"42063844 ","b":0.0,"c":1358.26,"d":1358.26,"e":"PAREDES CHANG ROBERT OSWALDO"},{"a":"001056362","b":0.0,"c":951.84,"d":951.84,"e":"PARADA CALVO, YOLANDA "},{"a":"42565274 ","b":0.0,"c":559.76,"d":559.76,"e":"PANDO PORTILLA MELISSA EMPERATRIZ "},{"a":"10721926 ","b":0.0,"c":849.16,"d":849.16,"e":"PALOMINO ROMERO CRISTOBAL "},{"a":"46795816 ","b":0.0,"c":610.76,"d":610.76,"e":"PALACIOS PORTOCARRERO HELEN ROXANA"},{"a":"10524265 ","b":0.0,"c":1507.27,"d":1507.27,"e":"PACHECO PEREZ, ALBERTO"},{"a":"001067424","b":0.0,"c":740.32,"d":740.32,"e":"OSORIO AGUIRRE, JONNY ALEJANDRO "},{"a":"46740545 ","b":0.0,"c":396.2,"d":396.2,"e":"ORE CASTRO TANIA PATRICIA "},{"a":"44288800 ","b":0.0,"c":887.43,"d":887.43,"e":"OCAÑA ROMERO ELIZABETH"},{"a":"43040848 ","b":0.0,"c":413.91,"d":413.91,"e":"OCAÑA ROMERO CARMEN "},{"a":"41755836 ","b":0.0,"c":1279.05,"d":1279.05,"e":"NUÑEZ PARIONA ROBERTO ARMANDO "},{"a":"45852769 ","b":0.0,"c":1281.21,"d":1281.21,"e":"NUÑEZ PARIONA ROBERT WILFREDO "},{"a":"09852083 ","b":0.0,"c":859.1,"d":859.1,"e":"NINACO CUBA JORGE "},{"a":"45745461 ","b":0.0,"c":1140.29,"d":1140.29,"e":"NARVASTA BERNAL, LUIS FIDEL "},{"a":"46827656 ","b":0.0,"c":687.44,"d":687.44,"e":"NAQUICHE RAMOS, MERY ROXANA "},{"a":"43336517 ","b":0.0,"c":638.94,"d":638.94,"e":"NAJARRO MUGURUZA JENNIFER JANE"},{"a":"45385427 ","b":0.0,"c":848.25,"d":848.25,"e":"NACCHA CASTILLO NESTOR AUGUSTO"},{"a":"47591128 ","b":0.0,"c":898.96,"d":898.96,"e":"MUÑOZ HUAMANI BRIGITTE"},{"a":"45372856 ","b":0.0,"c":1068.56,"d":1068.56,"e":"MUNGUIA SANDOVAL HERBERT DENIS"},{"a":"42809364 ","b":0.0,"c":783.84,"d":783.84,"e":"MOYA CASTILLO ELMER GUIDO "},{"a":"47437880 ","b":0.0,"c":781.1,"d":781.1,"e":"MOREYRA CHUPICA JOSEPH ELVIS"},{"a":"10337235 ","b":0.0,"c":864.39,"d":864.39,"e":"MONTES DE OCA SANCHEZ MARIA ESPERANZA "},{"a":"48096857 ","b":0.0,"c":522.68,"d":522.68,"e":"MONTES DE OCA CHUMIOQUE JUAN MAX"},{"a":"41403506 ","b":0.0,"c":1183.64,"d":1183.64,"e":"MONCADA MEDINA ELBER RUBEN"},{"a":"09952448 ","b":0.0,"c":665.96,"d":665.96,"e":"MONASTERIO CARBAJAL, LUIS ALONSO"},{"a":"70333472 ","b":0.0,"c":573.29,"d":573.29,"e":"MODESTO SONO, MARIELA LEONOR"},{"a":"71020941 ","b":0.0,"c":528.8,"d":528.8,"e":"MODESTO MONTES DE OCA KATHERINE "},{"a":"45537499 ","b":0.0,"c":793.2,"d":793.2,"e":"MELCHOR HUAYTA FREDY"},{"a":"000637354","b":0.0,"c":2637.57,"d":2637.57,"e":"MEJIA LOPEZ LUZ MIRIAN"},{"a":"45653372 ","b":0.0,"c":1073.33,"d":1073.33,"e":"MAYO SOTELO JAVIER ELMER"},{"a":"46735789 ","b":0.0,"c":745.0,"d":745.0,"e":"MAYNAS MARTINEZ MARLON EUGENIO"},{"a":"40419940 ","b":0.0,"c":1063.03,"d":1063.03,"e":"MARQUINA VILCAPOMA RUBEN"},{"a":"70115748 ","b":0.0,"c":782.14,"d":782.14,"e":"MARQUINA VILCAPOMA MANUEL "},{"a":"10731653 ","b":0.0,"c":386.1,"d":386.1,"e":"MANRIQUE HERENCIA MANUEL ANTONIO"},{"a":"45916418 ","b":0.0,"c":1026.0,"d":1026.0,"e":"MAMANI NOLAZCO SHYRLEY"},{"a":"42751959 ","b":0.0,"c":2325.94,"d":2325.94,"e":"MALCA URETA SANTOS MANUEL "},{"a":"42405389 ","b":0.0,"c":622.36,"d":622.36,"e":"MACULLUNCO BARRIENTOS, JORGE FRANCISCO"},{"a":"40574210 ","b":0.0,"c":872.15,"d":872.15,"e":"MACHACA QUISPE ADOLFO "},{"a":"07018424 ","b":0.0,"c":783.0,"d":783.0,"e":"LUQUE VARGAS LUIS "},{"a":"43388164 ","b":0.0,"c":823.22,"d":823.22,"e":"LUQUE ALZAMORA JUAN FELIX "},{"a":"41851928 ","b":0.0,"c":783.0,"d":783.0,"e":"LUQUE ALZAMORA JHON ANDRES"},{"a":"10096982 ","b":0.0,"c":822.65,"d":822.65,"e":"LOPEZ MIRANDA ARTURO"},{"a":"40226794 ","b":0.0,"c":1124.15,"d":1124.15,"e":"LOAYZA MUNAYA, SERGIO RUBEN "},{"a":"74595752 ","b":0.0,"c":888.96,"d":888.96,"e":"LLANOS CONCEPCION, YENI YOCELIN "},{"a":"47128327 ","b":0.0,"c":1107.26,"d":1107.26,"e":"LLANOS CONCEPCION FLOR CONSUELO "},{"a":"42019859 ","b":0.0,"c":823.22,"d":823.22,"e":"LIZANO RIVERA DARWIN"},{"a":"77487028 ","b":0.0,"c":674.22,"d":674.22,"e":"LA ROSA TORIBIO MILAGROS"},{"a":"000997954","b":0.0,"c":349.76,"d":349.76,"e":"JARAMILLO RODAS LUZ ELENIT"},{"a":"42765576 ","b":0.0,"c":1587.1,"d":1587.1,"e":"JARA CUZCANO IGNACIO JOSEPH "},{"a":"10240958 ","b":0.0,"c":977.77,"d":977.77,"e":"JARA CUZCANO GROVER NOE "},{"a":"70444760 ","b":0.0,"c":1091.46,"d":1091.46,"e":"HUERTAS CURAY THARINA "},{"a":"43641658 ","b":0.0,"c":822.18,"d":822.18,"e":"HUAYHUA HUAMANI EDWIN "},{"a":"45997439 ","b":0.0,"c":1229.54,"d":1229.54,"e":"HUARANCCA GALINDO MICHAEL DAYVIS"},{"a":"09822110 ","b":0.0,"c":1492.53,"d":1492.53,"e":"HUAPAYA TORIBIO VICTOR MANUEL "},{"a":"40976107 ","b":0.0,"c":1562.24,"d":1562.24,"e":"HUAPAYA TORIBIO MARCO ANTONIO "},{"a":"09829081 ","b":0.0,"c":924.63,"d":924.63,"e":"HUAPAYA TORIBIO ELIZABET"},{"a":"60974924 ","b":0.0,"c":713.12,"d":713.12,"e":"HUANCAS SALVADOR NEXAR DAVID"},{"a":"40964551 ","b":0.0,"c":821.33,"d":821.33,"e":"HUAMAN VARGAS ROBER DAN "},{"a":"42203949 ","b":0.0,"c":740.32,"d":740.32,"e":"HIJAR ESPINOZA, FREDDY MANUEL "},{"a":"10091177 ","b":0.0,"c":429.76,"d":429.76,"e":"HERRERA QUISPE ROBERTO CARLOS "},{"a":"10323977 ","b":0.0,"c":374.55,"d":374.55,"e":"HERRERA MALASQUEZ, REYNA DE MILAGROS"},{"a":"40142426 ","b":0.0,"c":783.84,"d":783.84,"e":"HACEN MORALES VICTOR MANUEL "},{"a":"40300060 ","b":0.0,"c":1115.41,"d":1115.41,"e":"GUTIERREZ OVIEDO ALFREDO"},{"a":"44086959 ","b":0.0,"c":782.22,"d":782.22,"e":"GUIZADO CANTARO PAULO CESAR "},{"a":"44410413 ","b":0.0,"c":1174.57,"d":1174.57,"e":"GUILLEN ALVARADO JOHNNATAN ANTONIO"},{"a":"01022902 ","b":0.0,"c":779.15,"d":779.15,"e":"GUERRA BRICEÑO EDISON "},{"a":"45469371 ","b":0.0,"c":429.68,"d":429.68,"e":"GRANADOS ROMERO HERMELINDA"},{"a":"44737131 ","b":0.0,"c":1117.49,"d":1117.49,"e":"GONZALEZ MORAN MARIO CARLOS "},{"a":"000511598","b":0.0,"c":2131.11,"d":2131.11,"e":"GONZALEZ CERRO HECTOR MARIANO "},{"a":"46868741 ","b":0.0,"c":768.08,"d":768.08,"e":"GONZALES MORAN SONY EMMANUEL"},{"a":"42269378 ","b":0.0,"c":1247.17,"d":1247.17,"e":"GONZALES CANCHO HERNAN GREGORIO "},{"a":"41658326 ","b":0.0,"c":1067.32,"d":1067.32,"e":"GIRON MUGURUZA GISSELA"},{"a":"001105702","b":0.0,"c":832.86,"d":832.86,"e":"GIRALDO MUÑOZ, JAVIER EDUARDO "},{"a":"47288994 ","b":0.0,"c":713.38,"d":713.38,"e":"GERONIMO CAMACHO VICTOR PAUL"},{"a":"42881323 ","b":0.0,"c":1865.96,"d":1865.96,"e":"GARRIDO VASQUEZ JOSE MARVIN "},{"a":"47123876 ","b":0.0,"c":783.0,"d":783.0,"e":"GARRIDO RODRIGUEZ JOSE ALBERTO"},{"a":"001158175","b":0.0,"c":793.2,"d":793.2,"e":"GARCIA GUERRERO, NORMA CONSTANZA"},{"a":"001073853","b":0.0,"c":1232.76,"d":1232.76,"e":"GARCIA GONZALES PAULA ANDREA"},{"a":"000731938","b":0.0,"c":752.59,"d":752.59,"e":"GARCIA BEDOYA JOSE ALBEIRO"},{"a":"46710303 ","b":0.0,"c":833.0,"d":833.0,"e":"GALARZA OSCANOA LUIS ALEJANDRO"},{"a":"70442866 ","b":0.0,"c":1139.21,"d":1139.21,"e":"FRANCO POLANCO PEDRO ANTONIO"},{"a":"41813633 ","b":0.0,"c":393.58,"d":393.58,"e":"FLORES PEÑA FIORELLA ANNET"},{"a":"44297039 ","b":0.0,"c":1471.48,"d":1471.48,"e":"FABIAN MALLMA, GISELLA ISABEL "},{"a":"45084030 ","b":0.0,"c":1109.45,"d":1109.45,"e":"ERAZO AREVALO HERNANDO"},{"a":"42804393 ","b":0.0,"c":779.15,"d":779.15,"e":"ENRIQUEZ PATI? HENRY PABLO"},{"a":"40551166 ","b":0.0,"c":823.22,"d":823.22,"e":"ECHACCAYA QUILCA JAVIER "},{"a":"48242298 ","b":0.0,"c":703.8,"d":703.8,"e":"DIAZ MONTES DE OCA ALEXA"},{"a":"70986911 ","b":0.0,"c":1000.15,"d":1000.15,"e":"DEL AGUILA LIMO JESUS ENRIQUE "},{"a":"43088119 ","b":0.0,"c":1026.48,"d":1026.48,"e":"DE LA CRUZ SALCEDO JORGE LUIS "},{"a":"44460916 ","b":0.0,"c":965.06,"d":965.06,"e":"DE LA CRUZ DE LA CRUZ, JAVIER ELMER "},{"a":"07443835 ","b":0.0,"c":435.9,"d":435.9,"e":"CORNEJO VALENCIA, JORGE LUIS"},{"a":"43700797 ","b":0.0,"c":387.43,"d":387.43,"e":"CORNEJO TUANAMA ANAIS CARMELA "},{"a":"42810189 ","b":0.0,"c":1043.26,"d":1043.26,"e":"CORDOBA CONDORPUZA RONALD JAMIS "},{"a":"20518702719","b":229422.88,"c":227390.52,"d":-2032.36,"e":"CONSTRUCERT SAC."},{"a":"41366434 ","b":0.0,"c":583.0,"d":583.0,"e":"CONDORI LOPEZ NIMER YOEL"},{"a":"46630880 ","b":0.0,"c":1034.6,"d":1034.6,"e":"CONDORI CHICAHUARI YSAAC"},{"a":"47080679 ","b":0.0,"c":883.87,"d":883.87,"e":"CHUZON SUCLUPE MICHAEL RUBEN"},{"a":"44127844 ","b":0.0,"c":1001.27,"d":1001.27,"e":"CHUQUILLANQUI VALENCIA CRISTHIAN GIOVANNI "},{"a":"43233153 ","b":0.0,"c":782.22,"d":782.22,"e":"CHOQUE VELASQUEZ MARCO ANTONIO"},{"a":"10744883 ","b":0.0,"c":1218.27,"d":1218.27,"e":"CHIPANA SIUPAUCAR FELIPE SILVESTRE"},{"a":"76237082 ","b":0.0,"c":634.56,"d":634.56,"e":"CHILON MONTES DE OCA SANDRA KARINA"},{"a":"45631162 ","b":0.0,"c":950.75,"d":950.75,"e":"CHAVEZ SALAZAR WILLIAN RONALD "},{"a":"40873667 ","b":0.0,"c":1042.96,"d":1042.96,"e":"CHAVEZ PERALES FIDEL LORENZO"},{"a":"41794059 ","b":0.0,"c":1376.57,"d":1376.57,"e":"CHAVESTA AYASTA EDGARG PEDRO"},{"a":"46086495 ","b":0.0,"c":1156.76,"d":1156.76,"e":"CHAVARRY SILVERA, THOMAS ROY EDUARDO"},{"a":"42582773 ","b":0.0,"c":544.46,"d":544.46,"e":"CAVERO MORAN PATRICIA "},{"a":"48126991 ","b":0.0,"c":766.9,"d":766.9,"e":"CAVALIER ALIAGA JOSEPH LOUIS"},{"a":"09700660 ","b":0.0,"c":782.22,"d":782.22,"e":"CASTRO FERNANDEZ RODRIGO"},{"a":"40277249 ","b":0.0,"c":823.59,"d":823.59,"e":"CASTRO FERNANDEZ REYNALDO "},{"a":"72945119 ","b":0.0,"c":783.0,"d":783.0,"e":"CARUZO CORDOVA LUIS "},{"a":"47350046 ","b":0.0,"c":561.15,"d":561.15,"e":"CARRAZCO MENDOZA, FLOR"},{"a":"43178280 ","b":0.0,"c":1097.87,"d":1097.87,"e":"CARLOS SILVERA JONATHAN WAGNER"},{"a":"70443975 ","b":0.0,"c":793.2,"d":793.2,"e":"CARHUAMACA VILCA JESUS"},{"a":"46303794 ","b":0.0,"c":1133.97,"d":1133.97,"e":"CARBAJAL TRUJILLO ANTHONY JESUS "},{"a":"45843857 ","b":0.0,"c":783.0,"d":783.0,"e":"CARAHUANCO VILCA RODOLFO JOSUE"},{"a":"000795464","b":0.0,"c":1268.15,"d":1268.15,"e":"CANO ECHEVERRY JOAQUIN EMILIO "},{"a":"45326292 ","b":0.0,"c":648.71,"d":648.71,"e":"CAMPOS QUISPE JOAN MANUEL "},{"a":"45922745 ","b":0.0,"c":690.2,"d":690.2,"e":"CAMPOS GUITTON IVAN CESAR "},{"a":"43249608 ","b":0.0,"c":1351.04,"d":1351.04,"e":"CALDERON MONTALBAN JUNIOR "},{"a":"09163049 ","b":0.0,"c":1818.88,"d":1818.88,"e":"CACERES DAVILA MARTHA ESPERANZA "},{"a":"10526747 ","b":0.0,"c":875.86,"d":875.86,"e":"CABRERA CASTRO SILA ELOISA"},{"a":"46652010 ","b":0.0,"c":702.39,"d":702.39,"e":"BUENDIA CHIPANA ANTHONY SATURNINO "},{"a":"72201593 ","b":0.0,"c":739.5,"d":739.5,"e":"BRICEÑO CASTILLO SARA LUZ "},{"a":"43109052 ","b":0.0,"c":1023.01,"d":1023.01,"e":"BORDA CACERES MARIBEL "},{"a":"45158599 ","b":0.0,"c":1107.26,"d":1107.26,"e":"BONILLA AYVAR MIGUEL ANGEL"},{"a":"000576801","b":0.0,"c":1067.32,"d":1067.32,"e":"BONETT PEREZ VERENA MARGARITA "},{"a":"07019306 ","b":0.0,"c":1761.59,"d":1761.59,"e":"BAUTISTA QUISPE ELENA "},{"a":"43578313 ","b":0.0,"c":941.26,"d":941.26,"e":"BARRIOS SANCHEZ RICARDO MODESTO "},{"a":"40481463 ","b":0.0,"c":968.46,"d":968.46,"e":"ATANACIO PUMACAYO YRMA"},{"a":"42038252 ","b":0.0,"c":793.2,"d":793.2,"e":"ARTEAGA CASTAÑEDA, CLOVIS "},{"a":"73211265 ","b":0.0,"c":784.38,"d":784.38,"e":"ARIAS MEJORADA, MERILY"},{"a":"001126803","b":0.0,"c":434.7,"d":434.7,"e":"ARCILA RENDON ELIANA ALEJANDRA"},{"a":"000935738","b":0.0,"c":1469.32,"d":1469.32,"e":"ARBELAEZ ARISTIZABAL HECTOR JAIME "},{"a":"42578718 ","b":0.0,"c":1596.28,"d":1596.28,"e":"ARANDA QUIROZ RICARDO GABINO"},{"a":"70006686 ","b":0.0,"c":1035.72,"d":1035.72,"e":"ANDRADE RIOS RICARDO RODOLFO"},{"a":"47946579 ","b":0.0,"c":783.84,"d":783.84,"e":"ANCCASI VILLANUEVA ROBERT "},{"a":"000637320","b":0.0,"c":3266.14,"d":3266.14,"e":"AMAYA MARIN JOHN JAIME"},{"a":"001007737","b":0.0,"c":3162.71,"d":3162.71,"e":"AMAYA CARO, BISMARCK"},{"a":"42234366 ","b":0.0,"c":386.06,"d":386.06,"e":"ALMEIDA PEÑA PATRICIA "},{"a":"08388881 ","b":0.0,"c":822.15,"d":822.15,"e":"ALFARO FLORES JORGE "},{"a":"000884734","b":0.0,"c":501.17,"d":501.17,"e":"AGUIRRE BATERO ORFA NERY"},{"a":"46904004 ","b":0.0,"c":565.5,"d":565.5,"e":"AGUILAR CAMPOS, KARINA EDITH"}]}
